llmclassbasedtoolregistry-0.1.0.dist-info/licenses/LICENSE
toolregistry/__init__.py
llmclassbasedtoolregistry-0.1.0.dist-info/METADATA
llmclassbasedtoolregistry-0.1.0.dist-info/WHEEL
llmclassbasedtoolregistry-0.1.0.dist-info/top_level.txt
llmclassbasedtoolregistry-0.1.0.dist-info/RECORD
